github_release_assets/__init__.py
github_release_assets/github.py
github_release_assets/plugin.py
github_release_assets/version.py
mkdocs_github_release_assets_plugin-0.0.6.dist-info/LICENSE
mkdocs_github_release_assets_plugin-0.0.6.dist-info/METADATA
mkdocs_github_release_assets_plugin-0.0.6.dist-info/WHEEL
mkdocs_github_release_assets_plugin-0.0.6.dist-info/entry_points.txt
mkdocs_github_release_assets_plugin-0.0.6.dist-info/top_level.txt
mkdocs_github_release_assets_plugin-0.0.6.dist-info/RECORD
