Metadata-Version: 2.1
Name: mkdocs-github-release-assets-plugin
Version: 0.0.6
Summary: MkDocs plugin to include GitHub release assets in the documentation
Author-email: Takeshi Yaegashi <yaegashi@gmail.com>
Maintainer-email: Takeshi Yaegashi <yaegashi@gmail.com>
License: MIT License
Project-URL: repository, https://github.com/yaegashi/mkdocs-github-release-assets-plugin
Project-URL: documentation, https://yaegashi.github.io/mkdocs-github-release-assets-plugin/
Keywords: mkdocs,mkdocs-plugin,github,documentation
License-File: LICENSE
Requires-Dist: ghapi
